odoo/addons/sm_onboarding_crm/__init__.py
odoo/addons/sm_onboarding_crm/__manifest__.py
odoo/addons/sm_onboarding_crm/data/crm_team_data.xml
odoo/addons/sm_onboarding_crm/data/utm_source_data.xml
odoo/addons/sm_onboarding_crm/models/__init__.py
odoo/addons/sm_onboarding_crm/models/crm_team.py
odoo/addons/sm_onboarding_crm/models/utm.py
odoo/addons/sm_onboarding_crm/services/__init__.py
odoo/addons/sm_onboarding_crm/services/crm_lead_service.py
odoo/addons/sm_onboarding_crm/services/schemas.py
odoo/addons/sm_onboarding_crm/views/crm_lead_views.xml
odoo/addons/sm_onboarding_crm/views/utm.xml
odoo12_addon_sm_onboarding_crm-12.0.0.0.6.dist-info/METADATA
odoo12_addon_sm_onboarding_crm-12.0.0.0.6.dist-info/WHEEL
odoo12_addon_sm_onboarding_crm-12.0.0.0.6.dist-info/top_level.txt
odoo12_addon_sm_onboarding_crm-12.0.0.0.6.dist-info/RECORD
