Metadata-Version: 2.1
Name: odoo12-addon-sm-onboarding-crm
Version: 12.0.0.0.6
Summary: onboarding customers and company employees with crm.lead
Home-page: https://git.coopdevs.org/coopdevs/odoo/odoo-addons/vertical-carsharing
Author: Som Mobilitat
License: UNKNOWN
Platform: UNKNOWN
Classifier: Programming Language :: Python
Classifier: Framework :: Odoo
Classifier: Framework :: Odoo :: 12.0
Requires-Python: >=3.5
Requires-Dist: odoo12-addon-crm-metadata
Requires-Dist: odoo12-addon-crm-metadata-rest-api
Requires-Dist: odoo12-addon-vertical-carsharing
Requires-Dist: odoo <12.1dev,>=12.0a
